README.rst
setup.py
django_field_object_permissions.egg-info/PKG-INFO
django_field_object_permissions.egg-info/SOURCES.txt
django_field_object_permissions.egg-info/dependency_links.txt
django_field_object_permissions.egg-info/requires.txt
django_field_object_permissions.egg-info/top_level.txt
fieldobjectpermissions/__init__.py
fieldobjectpermissions/apps.py
fieldobjectpermissions/backends.py