Metadata-Version: 1.1
Name: django-field-object-permissions
Version: 0.1.1
Summary: Provides an object permission system based on field values (eg: object.owner == user)
Home-page: http://github.com/aarcro/django-field-object-permissions
Author: Aaron McMillin
Author-email: fieldobject@aaron.mcmillinclan.org
License: MIT
Platform: UNKNOWN
Classifier: Development Status :: 2 - Pre-Alpha
Classifier: Intended Audience :: Developers
Classifier: License :: OSI Approved :: MIT License
Classifier: Natural Language :: English
Classifier: Framework :: Django
Classifier: Framework :: Django :: 1.7
Classifier: Framework :: Django :: 1.8
Classifier: Programming Language :: Python :: 2
Classifier: Programming Language :: Python :: 2.7
Classifier: Programming Language :: Python :: 3
Classifier: Programming Language :: Python :: 3.2
Classifier: Programming Language :: Python :: 3.3
Classifier: Programming Language :: Python :: 3.4
